{"backgrounds":[{"id":"82f7df92-c772-4261-8340-54ef146a157b","key":"background/gradient","active":true,"display":{"luminosity":0,"blur":0}}],"widgets":[{"id":"ab349f9d-f46d-49f3-a8ea-db76801e18ac","key":"widget/quote","active":true,"display":{"position":"middleCentre","fontFamily":"Fira Code","fontWeight":100,"colour":"#d91041"}},{"id":"84abac0d-a4f2-437e-88e9-b0f2e5c6fd78","key":"widget/weather","active":true,"display":{"position":"topRight","fontFamily":"sans","fontWeight":400,"colour":"#d3b6a8"}}],"data":{"236db75a-6e11-4e91-8fdd-f1527ed77a7e":{"by":"official","collections":"","featured":false,"search":"","timeout":86400},"a091f7ec-556d-415c-9b58-6d926d2d3a93":{"mode":"digital","hour12":false,"showDate":false,"showMinutes":true,"showSeconds":false,"showDayPeriod":true},"82f7df92-c772-4261-8340-54ef146a157b":{"angle":180,"from":"#5e3749","to":"#043546","type":"linear-gradient"},"0b0a89bc-461d-46fd-be39-928ad73eabb3":{"items":[],"show":3},"ab349f9d-f46d-49f3-a8ea-db76801e18ac":{"category":"developerexcuses"},"84abac0d-a4f2-437e-88e9-b0f2e5c6fd78":{"showDetails":true,"units":"auto","latitude":-29.4816568,"longitude":-51.813752,"name":""},"ec321db4-91c3-4d63-8ad9-db133f67a166":{"showBookAndAuthor":true,"centerText":false}},"locale":"pt-BR","_persist":{"version":-1,"rehydrated":true}}